atmos_toolbox/__init__.py
atmos_toolbox/download.py
atmos_toolbox/epe_detect.py
atmos_toolbox/fig_func.py
atmos_toolbox/hydro_utils.py
atmos_toolbox/lgr_mois_diag.py
atmos_toolbox/sph_harm.py
atmos_toolbox/stats_func.py
atmos_toolbox/std_index.py
atmos_toolbox/time_func.py
atmos_toolbox-3.6.0.dist-info/licenses/LICENSE
atmos_toolbox-3.6.0.dist-info/METADATA
atmos_toolbox-3.6.0.dist-info/WHEEL
atmos_toolbox-3.6.0.dist-info/top_level.txt
atmos_toolbox-3.6.0.dist-info/RECORD
