Metadata-Version: 2.4
Name: atmos_toolbox
Version: 3.6.0
Summary: A python toolbox for data analysis in meteorology & atmospheric sciences
Author: Mingxi Zhang
Author-email: zhang.mingxi@outlook.com
License-File: LICENSE
Dynamic: author
Dynamic: author-email
Dynamic: description
Dynamic: description-content-type
Dynamic: license-file
Dynamic: summary
